rasa_chinese/__init__.py
rasa_chinese/core/__init__.py
rasa_chinese/core/policies/__init__.py
rasa_chinese/core/policies/stacked_bilstm_paddle_policy.py
rasa_chinese/core/policies/stacked_bilstm_tf_policy.py
rasa_chinese/nlu/__init__.py
rasa_chinese/nlu/classifiers/__init__.py
rasa_chinese/nlu/classifiers/dense_network_tf_classifier.py
rasa_chinese/nlu/classifiers/ernie_classifier.py
rasa_chinese/nlu/classifiers/text_cnn_paddle_classifier.py
rasa_chinese/nlu/classifiers/text_cnn_tf_classifier.py
rasa_chinese/nlu/debugger/__init__.py
rasa_chinese/nlu/debugger/hooks.py
rasa_chinese/nlu/debugger/tensorflow_debugger.py
rasa_chinese/nlu/extractors/__init__.py
rasa_chinese/nlu/extractors/bilstm_crf_paddle_entity_extractor.py
rasa_chinese/nlu/extractors/bilstm_crf_tf_entity_extractor.py
rasa_chinese/nlu/featurizers/__init__.py
rasa_chinese/nlu/featurizers/base_featurizer.py
rasa_chinese/nlu/featurizers/bert_base.py
rasa_chinese/nlu/featurizers/bert_char_featurizer.py
rasa_chinese/nlu/featurizers/bert_text_featurizer.py
rasa_chinese/nlu/tokenizers/__init__.py
rasa_chinese/nlu/tokenizers/lm_tokenizer.py
rasa_chinese/nlu/tokenizers/micro_addons_tokenizer.py
rasa_chinese/nlu/utils/__init__.py
rasa_chinese/nlu/utils/paddle_utils.py
rasa_chinese/nlu/utils/tensorflow_utils.py
rasa_chinese/utils/__init__.py
rasa_chinese/utils/trainning.py
tests/__init__.py
tests/nlu/__init__.py
tests/nlu/tokenizers/__init__.py
tests/nlu/tokenizers/test_lm_tokenizer.py
rasa_chinese-2.2.0.dist-info/LICENSE
rasa_chinese-2.2.0.dist-info/METADATA
rasa_chinese-2.2.0.dist-info/WHEEL
rasa_chinese-2.2.0.dist-info/top_level.txt
rasa_chinese-2.2.0.dist-info/RECORD
